{
  "entrypoints": [
    "main"
  ],
  "origins": {
    "972": [
      972
    ],
    "17896441": [
      532,
      918
    ],
    "main": [
      303,
      532,
      179
    ],
    "runtime~main": [
      179,
      532,
      303
    ],
    "1be78505": [
      532,
      972
    ],
    "3b8c55ea": [
      217
    ],
    "4ead559e": [
      145
    ],
    "74a803a9": [
      364
    ],
    "92bb876c": [
      347
    ],
    "935f2afb": [
      53
    ],
    "a3cbdead": [
      372
    ],
    "c4f5d8e4": [
      532,
      195
    ],
    "d25f097e": [
      934
    ],
    "e747ec83": [
      291
    ],
    "f56d8649": [
      38
    ],
    "styles": [
      179,
      195,
      303,
      514,
      918,
      532
    ]
  },
  "assets": {
    "38": {
      "js": [
        {
          "file": "assets/js/f56d8649.f855f456.js",
          "hash": "0782946077afbaa4",
          "publicPath": "/assets/js/f56d8649.f855f456.js"
        }
      ]
    },
    "53": {
      "js": [
        {
          "file": "assets/js/935f2afb.82f3050d.js",
          "hash": "f07e1849933f3bf8",
          "publicPath": "/assets/js/935f2afb.82f3050d.js"
        }
      ]
    },
    "145": {
      "js": [
        {
          "file": "assets/js/4ead559e.fab40983.js",
          "hash": "224f1580fed261a9",
          "publicPath": "/assets/js/4ead559e.fab40983.js"
        }
      ]
    },
    "179": {
      "js": [
        {
          "file": "assets/js/main.eef1a5ad.js",
          "hash": "3d61582d48d907a9",
          "publicPath": "/assets/js/main.eef1a5ad.js"
        }
      ]
    },
    "195": {
      "js": [
        {
          "file": "assets/js/c4f5d8e4.f9372839.js",
          "hash": "21163954871672a7",
          "publicPath": "/assets/js/c4f5d8e4.f9372839.js"
        }
      ]
    },
    "217": {
      "js": [
        {
          "file": "assets/js/3b8c55ea.0157b7e5.js",
          "hash": "b054ad68b376c133",
          "publicPath": "/assets/js/3b8c55ea.0157b7e5.js"
        }
      ]
    },
    "291": {
      "js": [
        {
          "file": "assets/js/e747ec83.7f65bc57.js",
          "hash": "d6ba8b8717284fe9",
          "publicPath": "/assets/js/e747ec83.7f65bc57.js"
        }
      ]
    },
    "303": {
      "js": [
        {
          "file": "assets/js/runtime~main.97a7b633.js",
          "hash": "666a216bda4c0adf",
          "publicPath": "/assets/js/runtime~main.97a7b633.js"
        }
      ]
    },
    "347": {
      "js": [
        {
          "file": "assets/js/92bb876c.7bfcc155.js",
          "hash": "f62084b38afe8741",
          "publicPath": "/assets/js/92bb876c.7bfcc155.js"
        }
      ]
    },
    "364": {
      "js": [
        {
          "file": "assets/js/74a803a9.89de6a48.js",
          "hash": "af11525725bcc1c1",
          "publicPath": "/assets/js/74a803a9.89de6a48.js"
        }
      ]
    },
    "372": {
      "js": [
        {
          "file": "assets/js/a3cbdead.9787379c.js",
          "hash": "20529f81aed205f5",
          "publicPath": "/assets/js/a3cbdead.9787379c.js"
        }
      ]
    },
    "532": {
      "css": [
        {
          "file": "assets/css/styles.d8c7080d.css",
          "hash": "9bf94f74e4ff18d9",
          "publicPath": "/assets/css/styles.d8c7080d.css"
        }
      ]
    },
    "918": {
      "js": [
        {
          "file": "assets/js/17896441.2164ce4e.js",
          "hash": "184124025cf26087",
          "publicPath": "/assets/js/17896441.2164ce4e.js"
        }
      ]
    },
    "934": {
      "js": [
        {
          "file": "assets/js/d25f097e.7626a68d.js",
          "hash": "f3ef10613190c093",
          "publicPath": "/assets/js/d25f097e.7626a68d.js"
        }
      ]
    },
    "972": {
      "js": [
        {
          "file": "assets/js/972.c14b7d18.js",
          "hash": "40c094e682593a9f",
          "publicPath": "/assets/js/972.c14b7d18.js"
        },
        {
          "file": "assets/js/1be78505.e139d558.js",
          "hash": "09a32c4db5fb6f94",
          "publicPath": "/assets/js/1be78505.e139d558.js"
        }
      ]
    }
  }
}